mesonic/__init__.py
mesonic/buffer.py
mesonic/context.py
mesonic/events.py
mesonic/playback.py
mesonic/processor.py
mesonic/record.py
mesonic/synth.py
mesonic/timeline.py
mesonic/backend/__init__.py
mesonic/backend/backend_sc3nb.py
mesonic/backend/bases.py
mesonic-0.2.0.dist-info/AUTHORS.rst
mesonic-0.2.0.dist-info/LICENSE.txt
mesonic-0.2.0.dist-info/METADATA
mesonic-0.2.0.dist-info/WHEEL
mesonic-0.2.0.dist-info/top_level.txt
mesonic-0.2.0.dist-info/RECORD
